[
  {
    "law": "특허법(대리·개별대리)",
    "link": "https://www.law.go.kr/",
    "truths": [
      "대리인이 2인 이상이면 각자 대리한다."
    ],
    "traps": [
      "대리인이 2인 이상이면 공동대리만 가능하다.",
      "대표대리인을 지정해야만 대리권이 발생한다."
    ],
    "note": "개별대리 원칙",
    "cat": "본문"
  },
  {
    "law": "특허법(추후보완)",
    "link": "https://www.law.go.kr/",
    "truths": [
      "사유 소멸일부터 2개월 내 보완 가능하나 원 만료일부터 1년 경과 시 불가하다."
    ],
    "traps": [
      "사유 소멸 후 {숫자}{단위} 내에는 언제든 보완 가능하고 1년 상한은 없다.",
      "추후보완은 기간 종류와 무관하게 일률 허용된다."
    ],
    "note": "2개월/1년 상한 함정",
    "cat": "본문"
  },
  {
    "law": "특허법(진보성)",
    "link": "https://www.law.go.kr/",
    "truths": [
      "통상의 기술자가 용이하게 발명할 수 있으면 특허불가."
    ],
    "traps": [
      "신규성만 있으면 진보성 없어도 특허 가능.",
      "통상의 기술자 기준시점은 출원공고일이다."
    ],
    "note": "진보성 기준 혼동",
    "cat": "본문"
  },
  {
    "law": "특허법(선출원)",
    "link": "https://www.law.go.kr/",
    "truths": [
      "동일발명은 먼저 출원한 자만 특허 가능."
    ],
    "traps": [
      "국내우선권 주장에는 선출원주의가 적용되지 않는다.",
      "동일발명이라도 공동으로 특허 가능."
    ],
    "note": "선출원주의",
    "cat": "본문"
  },
  {
    "law": "특허법(분할출원)",
    "link": "https://www.law.go.kr/",
    "truths": [
      "분할출원은 원출원의 일부 또는 전부를 분할하여 가능하며, 신규사항 추가는 불가하다."
    ],
    "traps": [
      "분할출원은 거절이유통지 전까지만 가능하다.",
      "분할출원에서도 신규사항 추가가 허용된다.",
      "분할출원은 원출원과 별개로 출원일 소급이 인정되지 않는다."
    ],
    "note": "시기·신규사항·소급효",
    "cat": "본문"
  },
  {
    "law": "특허법(명세서·상세한 설명)",
    "link": "https://www.law.go.kr/",
    "truths": [
      "명세서에는 발명의 상세한 설명이 기재되어야 한다."
    ],
    "traps": [
      "상세한 설명이 없어도 보정으로 항상 보완 가능.",
      "도면이 없으면 명세서는 무효다."
    ],
    "note": "보정 한계",
    "cat": "본문"
  },
  {
    "law": "특허법(보정범위)",
    "link": "https://www.law.go.kr/",
    "truths": [
      "최초 거절이유통지 후 신규 청구항 신설은 제한된다."
    ],
    "traps": [
      "거절이유통지 후에도 청구항 자유 신설 가능.",
      "보정 범위 제한이 없다."
    ],
    "note": "신규사항 금지",
    "cat": "본문"
  },
  {
    "law": "특허법(우선권)",
    "link": "https://www.law.go.kr/",
    "truths": [
      "조약 우선권은 최초 출원일부터 1년 내 주장."
    ],
    "traps": [
      "1년6개월까지 가능.",
      "기간 제한이 없다."
    ],
    "note": "기간 함정",
    "cat": "본문"
  },
  {
    "law": "특허법(출원공개)",
    "link": "https://www.law.go.kr/",
    "truths": [
      "우선권이 있으면 기초 출원일 기준 18개월 경과 시 공개, 조기공개 신청 가능."
    ],
    "traps": [
      "조기공개 제도가 없다.",
      "항상 국내출원일 기준이다."
    ],
    "note": "기준일/조기공개",
    "cat": "본문"
  },
  {
    "law": "특허법(존속기간)",
    "link": "https://www.law.go.kr/",
    "truths": [
      "특허권 존속기간은 출원일 후 20년."
    ],
    "traps": [
      "설정등록일부터 20년.",
      "우선권 주장일부터 20년."
    ],
    "note": "기산점",
    "cat": "본문"
  },
  {
    "law": "특허법(연장)",
    "link": "https://www.kipo.go.kr/",
    "truths": [
      "허가등 연장은 1회·최대 5년·허가일부터 14년 상한."
    ],
    "traps": [
      "연장 횟수 제한 없다.",
      "최대 10년 가능.",
      "14년 상한 없다."
    ],
    "note": "개정 반영",
    "cat": "본문"
  },
  {
    "law": "특허법(자료제출명령)",
    "link": "https://www.law.go.kr/",
    "truths": [
      "법원은 신청에 따라 상대방에게 자료제출 명할 수 있다."
    ],
    "traps": [
      "법원은 자료제출명령 불가.",
      "행정기관만 가능."
    ],
    "note": "절차",
    "cat": "본문"
  },
  {
    "law": "특허법(거절결정불복심판)",
    "link": "https://law.go.kr/",
    "truths": [
      "결정등본 송달일부터 3개월 내 청구 가능."
    ],
    "traps": [
      "{기산} 기준 {숫자}{단위} 이내.",
      "송달일과 무관하게 언제든 가능."
    ],
    "note": "기간/기산 트랩",
    "cat": "본문"
  },
  {
    "law": "특허법(심결취소소송)",
    "link": "https://www.kipo.go.kr/",
    "truths": [
      "송달일부터 30일 이내, 불변기간."
    ],
    "traps": [
      "{숫자}{단위} 이내면 된다.",
      "불변기간이 아니다."
    ],
    "note": "30일·불변기간",
    "cat": "본문"
  },
  {
    "law": "민법(초일불산입)",
    "link": "https://www.law.go.kr/",
    "truths": [
      "기간을 일·주·월·연으로 정한 때 초일은 불산입이 원칙."
    ],
    "traps": [
      "초일 산입이 원칙.",
      "형사소송에만 적용."
    ],
    "note": "기간 계산",
    "cat": "본문"
  }
]