[
  {
    "cat": "판례",
    "law": "무효심판 적격",
    "truths": [
      "특허무효심판은 원칙적으로 누구든지 청구할 수 있다."
    ],
    "traps": [
      "무효심판은 권리자만 청구 가능하다.",
      "무효심판은 이해관계인만 청구 가능하다."
    ],
    "note": "적격 범위(원칙)",
    "link": "https://glaw.scourt.go.kr/"
  },
  {
    "cat": "본문",
    "law": "정정심판 범위",
    "truths": [
      "정정으로 신규사항을 추가하는 것은 허용되지 않는다."
    ],
    "traps": [
      "정정으로 신규사항 추가가 가능하다.",
      "정정으로 청구범위를 언제나 확장할 수 있다."
    ],
    "note": "정정심판",
    "link": "https://www.law.go.kr/법령/특허법"
  },
  {
    "cat": "본문",
    "law": "심결취소소송 관할",
    "truths": [
      "심결취소소송은 관할 법원에 제기하며, 불변기간 내 제소하여야 한다."
    ],
    "traps": [
      "심결취소소송에는 제소기간 제한이 없다.",
      "지방법원 어디든 제기할 수 있다."
    ],
    "note": "소송 개요",
    "link": "https://www.law.go.kr/법령/특허법"
  }
]